setup.py
django_reportato.egg-info/PKG-INFO
django_reportato.egg-info/SOURCES.txt
django_reportato.egg-info/dependency_links.txt
django_reportato.egg-info/not-zip-safe
django_reportato.egg-info/top_level.txt
reportato/__init__.py
reportato/models.py
reportato/reporters.py
reportato/tests.py
reportato/utils.py
reportato/views.py