Metadata-Version: 1.1
Name: django-reportato
Version: 1.0
Summary: Very simple CSV reports with Django
Home-page: https://github.com/potatolondon/reportato
Author: Pablo Recio
Author-email: pablo@potatolondon.com
License: BSD
Keywords: django reports potato csv
Platform: UNKNOWN
Classifier: Development Status :: 4 - Beta
Classifier: Framework :: Django
Classifier: Intended Audience :: Developers
Classifier: License :: OSI Approved :: BSD License
Classifier: Operating System :: OS Independent
Classifier: Programming Language :: Python
